ime/__init__.py
ime/config.py
ime/engine.py
ime/trie.py
ime/utils.py
ime-0.0.1.dist-info/METADATA
ime-0.0.1.dist-info/RECORD
ime-0.0.1.dist-info/WHEEL
ime-0.0.1.dist-info/top_level.txt
tests/__init__.py
tests/test_trie.py
