Metadata-Version: 2.1
Name: ime
Version: 0.0.1
Summary: Yet another Chinese input method engine
Home-page: https://github.com/kemingy/ime
Author: Keming Yang
Author-email: kemingy94@gmail.com
License: UNKNOWN
Platform: UNKNOWN
Classifier: Programming Language :: Python :: 3
Classifier: License :: OSI Approved :: MIT License
Classifier: Operating System :: OS Independent
Requires-Dist: pypinyin (>=0.31.0)
